PyMML/PXIControl.py
PyMML/PostProcessing.py
PyMML/PreProcessing.py
PyMML/StoreSetup.py
PyMML/__init__.py
PyMeas/PXIControl.py
PyMeas/PostProcessing.py
PyMeas/PreProcessing.py
PyMeas/StoreSetup.py
PyMeas/__init__.py
PyPXI/PXIControl.py
PyPXI/PostProcessing.py
PyPXI/PreProcessing.py
PyPXI/StoreSetup.py
PyPXI/__init__.py
PyPXIControl/PXIControl.py
PyPXIControl/PostProcessing.py
PyPXIControl/PreProcessing.py
PyPXIControl/StoreSetup.py
PyPXIControl/__init__.py
PyPXIControl-1.0.0.dist-info/METADATA
PyPXIControl-1.0.0.dist-info/WHEEL
PyPXIControl-1.0.0.dist-info/top_level.txt
PyPXIControl-1.0.0.dist-info/RECORD
